{
  "title": "香港",
  "description": "",
  "custom_thumbnail": "20231011-P1060505.jpg",
  "datetime": "202310110000",
  "images": {
    "20231011-P1060174.jpg": {
        "description": ""
    },
    "20231011-P1060176.jpg": {
        "description": ""
    },
    "20231011-P1060177.jpg": {
        "description": ""
    },
    "20231011-P1060198.jpg": {
        "description": ""
    },
    "20231011-P1060200.jpg": {
        "description": ""
    },
    "20231011-P1060205.jpg": {
        "description": ""
    },
    "20231011-P1060216.jpg": {
        "description": ""
    },
    "20231011-P1060247.jpg": {
        "description": ""
    },
    "20231011-P1060503.jpg": {
        "description": ""
    },
    "20231011-P1060505.jpg": {
        "description": ""
    },
    "20231011-P1060514.jpg": {
        "description": ""
    },
    "20231011-P1060592.jpg": {
        "description": ""
    }
  }
}
