{
  "title": "潮汕",
  "description": "",
  "custom_thumbnail": "20250131-DSC00252.jpg",
  "datetime": "202501310000",
  "images": {
    "20250130-DSC00126.jpg": {
        "description": ""
    },
    "20250131-DSC00174.jpg": {
        "description": ""
    },
    "20250131-DSC00200.jpg": {
        "description": ""
    },
    "20250131-DSC00241.jpg": {
        "description": ""
    },
    "20250131-DSC00244.jpg": {
        "description": ""
    },
    "20250131-DSC00252.jpg": {
        "description": ""
    },
    "20250131-DSC00256.jpg": {
        "description": ""
    },
    "20250131-DSC00272.jpg": {
        "description": ""
    },
    "20250204-DSC00312.jpg": {
        "description": ""
    },
    "20250204-DSC00320.jpg": {
        "description": ""
    },
    "20250204-DSC00336.jpg": {
        "description": ""
    },
    "20250204-DSC00420.jpg": {
        "description": ""
    },
    "20250204-DSC00439.jpg": {
        "description": ""
    },
    "20250204-DSC00447.jpg": {
        "description": ""
    },
    "20250204-DSC00473.jpg": {
        "description": ""
    },
    "20250204-IMG_3291.jpg": {
        "description": ""
    },
    "20250205-IMG_3302.jpg": {
        "description": ""
    }
  }
}
